{
  "$schema": "https://json-schema.org/draft/2020-12/schema",
  "title": "Env",
  "description": "Environment configuration with environment-specific overrides\nBased on schema/env.cue",
  "type": "object",
  "properties": {
    "environment": {
      "description": "Environment-specific overrides",
      "type": ["object", "null"],
      "additionalProperties": {
        "type": "object",
        "additionalProperties": {
          "$ref": "#/$defs/EnvValue"
        }
      }
    }
  },
  "additionalProperties": {
    "$ref": "#/$defs/EnvValue"
  },
  "$defs": {
    "EnvValue": {
      "description": "Environment variable values can be strings, integers, booleans, secrets, or values with policies\nWhen exported to actual environment, these will always be strings",
      "anyOf": [
        {
          "$ref": "#/$defs/EnvVarWithPolicies"
        },
        {
          "type": "string"
        },
        {
          "type": "integer",
          "format": "int64"
        },
        {
          "type": "boolean"
        },
        {
          "$ref": "#/$defs/Secret"
        }
      ]
    },
    "EnvValueSimple": {
      "description": "Simple environment variable values (non-recursive)",
      "anyOf": [
        {
          "type": "string"
        },
        {
          "type": "integer",
          "format": "int64"
        },
        {
          "type": "boolean"
        },
        {
          "$ref": "#/$defs/Secret"
        }
      ]
    },
    "EnvVarWithPolicies": {
      "description": "Environment variable with optional access policies",
      "type": "object",
      "properties": {
        "policies": {
          "description": "Optional access policies",
          "type": ["array", "null"],
          "items": {
            "$ref": "#/$defs/Policy"
          }
        },
        "value": {
          "description": "The actual value",
          "$ref": "#/$defs/EnvValueSimple"
        }
      },
      "required": ["value"]
    },
    "Policy": {
      "description": "Policy for controlling environment variable access",
      "type": "object",
      "properties": {
        "allowExec": {
          "description": "Allowlist of exec commands that can access this variable",
          "type": ["array", "null"],
          "items": {
            "type": "string"
          }
        },
        "allowTasks": {
          "description": "Allowlist of task names that can access this variable",
          "type": ["array", "null"],
          "items": {
            "type": "string"
          }
        }
      }
    },
    "Secret": {
      "description": "Secret definition with resolver\nThis is the base type that can be extended in CUE",
      "type": "object",
      "properties": {
        "args": {
          "description": "Arguments to pass to the command",
          "type": "array",
          "default": [],
          "items": {
            "type": "string"
          }
        },
        "command": {
          "description": "Command to execute",
          "type": "string"
        },
        "resolver": {
          "description": "Resolver type (currently only \"exec\" is supported)",
          "type": "string"
        }
      },
      "additionalProperties": true,
      "required": ["resolver", "command"]
    }
  }
}
